example_package/__init__.py
example_package/example.py
bigluotest-0.0.4.dist-info/LICENSE
bigluotest-0.0.4.dist-info/METADATA
bigluotest-0.0.4.dist-info/WHEEL
bigluotest-0.0.4.dist-info/top_level.txt
bigluotest-0.0.4.dist-info/RECORD
